{
    "$schema": "https://glama.ai/mcp/schemas/server.json",
    "maintainers": ["cryptorugmuncher"],
    "name": "Rug Munch Intelligence x402 Gateway (Solana)",
    "description": "175 crypto security & analytics tools via x402 micropayments on Solana. 21 RMI tools (contract audit, rug detection, wallet profiling, social analysis) + 154 MCP tools (DexScreener, Jupiter, Birdeye, GMGN, Arkham, Nansen, CoinGecko, DeFiLlama, and 20 more). From $0.01/call with free trials. No API keys needed.",
    "server": {
        "url": "https://x402-sol.cryptorugmuncher.workers.dev",
        "transport": "http",
        "capabilities": {
            "tools": {
                "listChanged": true
            }
        }
    }
}